pyrepka/__init__.py
pyrepka/py_repka.py
pyrepka-1.0.1.dist-info/METADATA
pyrepka-1.0.1.dist-info/WHEEL
pyrepka-1.0.1.dist-info/top_level.txt
pyrepka-1.0.1.dist-info/RECORD
