Metadata-Version: 2.1
Name: pyrepka
Version: 1.0.1
Summary: Модуль для работы с реферальной программой "Репка"
Home-page: https://github.com/oshkov/py-repka
Author: oshkov
Author-email: sasha.oshkov03@gmail.com
Project-URL: GitHub, https://github.com/oshkov
Keywords: Реферальная программа
Classifier: Programming Language :: Python :: 3.10
Classifier: License :: OSI Approved :: MIT License
Classifier: Operating System :: OS Independent
Requires-Python: >=3.6
Requires-Dist: requests
